ctrlc/__init__.py
ctrlc/cli.py
ctrlc/config.py
ctrlc/core.py
ctrlc/ignore.py
ctrlc_cli-1.0.1.dist-info/LICENSE
ctrlc_cli-1.0.1.dist-info/METADATA
ctrlc_cli-1.0.1.dist-info/WHEEL
ctrlc_cli-1.0.1.dist-info/entry_points.txt
ctrlc_cli-1.0.1.dist-info/RECORD
