Metadata-Version: 2.3
Name: ctrlc-cli
Version: 1.0.1
Summary: Bundle project codebase into text or compressed outputs for easy LLM ingestion, debugging and sharing
License: MIT
Author: Advaith Sanil Kumar advaithsanilkumar@gmail.com
Requires-Python: >=3.8
Classifier: License :: OSI Approved :: MIT License
Classifier: Programming Language :: Python :: 3
Classifier: Programming Language :: Python :: 3.8
Classifier: Programming Language :: Python :: 3.9
Classifier: Programming Language :: Python :: 3.10
Classifier: Programming Language :: Python :: 3.11
Classifier: Programming Language :: Python :: 3.12
Classifier: Programming Language :: Python :: 3.13
Requires-Dist: click (>=8.0,<9.0)
Requires-Dist: pathspec (>=0.11.1,<0.12.0)
Requires-Dist: rich (>=14.0.0,<15.0.0)
Requires-Dist: toml (>=0.10.2,<0.11.0)
